yors_pano_action_handle/__init__.py
yors_pano_action_handle/main.py
yors_pano_action_handle-0.1.0.dist-info/METADATA
yors_pano_action_handle-0.1.0.dist-info/WHEEL
yors_pano_action_handle-0.1.0.dist-info/RECORD
