Metadata-Version: 2.1
Name: yors_pano_action_handle
Version: 0.1.0
Summary: a package named yors_pano_action_handle
Home-page: https://github.com//blob/main/packages/yors_pano_action_handle/README.md
License: LICENSE
Keywords: artist,panz,mono,yors_pano_action_handle
Author: yemiancheng
Author-email: ymc.github@gmail.com
Requires-Python: >=3.10,<4.0
Classifier: Development Status :: 3 - Alpha
Classifier: Intended Audience :: Developers
Classifier: License :: OSI Approved :: MIT License
Classifier: License :: Other/Proprietary License
Classifier: Programming Language :: Python :: 3
Classifier: Programming Language :: Python :: 3.10
Classifier: Programming Language :: Python :: 3.11
Classifier: Programming Language :: Python :: 3.12
Classifier: Topic :: Software Development :: Build Tools
Project-URL: Documentation, https://github.com//blob/main/packages/yors_pano_action_handle/README.md
Project-URL: Repository, https://github.com/.git
Project-URL: changelog, https://github.com//blob/main/packages/yors_pano_action_handle/CHANGELOG.md
